netbox_ninja_plugin/__init__.py
netbox_ninja_plugin/api/serializers.py
netbox_ninja_plugin/api/urls.py
netbox_ninja_plugin/api/views.py
netbox_ninja_plugin/helpers.py
netbox_ninja_plugin/migrations/0001_initial.py
netbox_ninja_plugin/migrations/__init__.py
netbox_ninja_plugin/models.py
netbox_ninja_plugin/navigation.py
netbox_ninja_plugin/ninja_template/__init__.py
netbox_ninja_plugin/ninja_template/choices.py
netbox_ninja_plugin/ninja_template/filtersets.py
netbox_ninja_plugin/ninja_template/forms.py
netbox_ninja_plugin/ninja_template/logic.py
netbox_ninja_plugin/ninja_template/models.py
netbox_ninja_plugin/ninja_template/tables.py
netbox_ninja_plugin/ninja_template/views.py
netbox_ninja_plugin/signals.py
netbox_ninja_plugin/static/netbox_ninja_plugin/js/viewer-loader.js
netbox_ninja_plugin/static/netbox_ninja_plugin/js/viewer-static.min.js
netbox_ninja_plugin/templates/netbox_ninja_plugin/_drawio_script.html
netbox_ninja_plugin/templates/netbox_ninja_plugin/ninja_tab.html
netbox_ninja_plugin/templates/netbox_ninja_plugin/ninjatemplate.html
netbox_ninja_plugin/templatetags/ninja_tags.py
netbox_ninja_plugin/tests/__init__.py
netbox_ninja_plugin/tests/test_forms.py
netbox_ninja_plugin/tests/test_views.py
netbox_ninja_plugin/urls.py
netbox_ninja_plugin-0.1.13.dist-info/METADATA
netbox_ninja_plugin-0.1.13.dist-info/WHEEL
netbox_ninja_plugin-0.1.13.dist-info/licenses/LICENSE
netbox_ninja_plugin-0.1.13.dist-info/RECORD
