Metadata-Version: 2.4
Name: netbox-ninja-plugin
Version: 0.1.13
Summary: Dynamic configuration files and images from NetBox.
License: MIT
License-File: LICENSE
Author: Veikko Pankakoski
Author-email: veikko@rautanen.io
Requires-Python: >=3.11,<4.0
Classifier: License :: OSI Approved :: MIT License
Classifier: Operating System :: OS Independent
Classifier: Programming Language :: Python :: 3
Classifier: Programming Language :: Python :: 3.11
Classifier: Programming Language :: Python :: 3.12
Classifier: Programming Language :: Python :: 3.13
Classifier: Programming Language :: Python :: 3.14
Requires-Dist: lxml (>=5.0,<7.0)
Requires-Dist: requests (>=2.32.2,<3.0.0)
Project-URL: Documentation, https://github.com/rautanen-io/netbox-ninja-plugin
Project-URL: Homepage, https://rautanen.io
Project-URL: Repository, https://github.com/rautanen-io/netbox-ninja-plugin
